eye_of_horus/__init__.py
eye_of_horus/bitwise.py
eye_of_horus/corpus.py
eye_of_horus/engine.py
eye_of_horus/mapping.py
eye_of_horus/pyramid.py
eye_of_horus/rhythm.py
eye_of_horus/validation.py
eye_of_horus/data/pyramid_texts_translated.json
eye_of_horus/data/semantic_network.json
eye_of_horus-0.6.0.dist-info/METADATA
eye_of_horus-0.6.0.dist-info/WHEEL
eye_of_horus-0.6.0.dist-info/licenses/LICENSE
eye_of_horus-0.6.0.dist-info/RECORD
