Metadata-Version: 2.4
Name: eye-of-horus
Version: 0.6.0
Summary: Phonemic analysis engine for ancient Egyptian texts — 16-position wheel, 408 grammar, bidirectional decode
Project-URL: Homepage, https://github.com/NickBrownAI/EyeOfHorus
Project-URL: Repository, https://github.com/NickBrownAI/EyeOfHorus
Project-URL: Documentation, https://github.com/NickBrownAI/EyeOfHorus#readme
Author-email: Nicholas David Brown <worldbridgerstudios@gmail.com>
License-Expression: CC0-1.0
License-File: LICENSE
Keywords: ancient,computational-linguistics,egyptian,hieroglyphics,linguistics,phonemic,pyramid-texts,translation
Classifier: Development Status :: 4 - Beta
Classifier: Intended Audience :: Science/Research
Classifier: License :: OSI Approved :: MIT License
Classifier: Programming Language :: Python :: 3
Classifier: Programming Language :: Python :: 3.10
Classifier: Programming Language :: Python :: 3.11
Classifier: Programming Language :: Python :: 3.12
Classifier: Programming Language :: Python :: 3.13
Classifier: Programming Language :: Python :: 3.14
Classifier: Topic :: Scientific/Engineering :: Artificial Intelligence
Classifier: Topic :: Text Processing :: Linguistic
Requires-Python: >=3.10
Provides-Extra: dev
Requires-Dist: black; extra == 'dev'
Requires-Dist: pytest; extra == 'dev'
Requires-Dist: ruff; extra == 'dev'
